tinydrawer/__init__.py
tinydrawer/tinydrawer.py
tinydrawer-0.0.9.dist-info/METADATA
tinydrawer-0.0.9.dist-info/WHEEL
tinydrawer-0.0.9.dist-info/top_level.txt
tinydrawer-0.0.9.dist-info/RECORD
